matlab_path/__init__.py
matlab_path/main.py
matlab_path/matlab/__init__.py
matlab_path/matlab/attributes.py
matlab_path/matlab/nodes.py
matlab_path/matlab/parser.py
matlab_path/matlab/utils.py
matlab_search_path_resolver-0.1.0.dist-info/LICENSE
matlab_search_path_resolver-0.1.0.dist-info/METADATA
matlab_search_path_resolver-0.1.0.dist-info/WHEEL
matlab_search_path_resolver-0.1.0.dist-info/RECORD
